Workbook

Sheet สรุปการส่งออก
B3: เอกสารนี้ได้ส่งออกจาก Numbers ตารางแต่ละตารางได้แปลงเป็นแผ่นงานแบบ Excel วัตถุอื่นทั้งหมดของแผ่นงานแบบ Numbers แต่ละแผ่นได้แยกออกจากกันเป็นแผ่น โปรดทราบว่าการคำนวณของสูตรอาจแตกต่างจาก Excel
B7: ชื่อแผ่นงาน Numbers | C7: ชื่อตาราง Numbers | D7: ชื่อแผ่นงาน Excel
B9: Dashboard
C10: ตาราง 1 | D10: Dashboard
B11: Transactions
C12: ตาราง 1 | D12: Transactions
B13: Projects
C14: ตาราง 1 | D14: Projects
B15: Invoices
C16: ตาราง 1 | D16: Invoices
B17: Read Me
C18: ตาราง 1 | D18: Read Me

Sheet Dashboard
A1: PERSONAL FINANCE | SEPTEMBER 2026
A3: Profile | B3: Alex Morgan | D3: METRIC
A4: Period | B4: Sep 1–30, 2026 | D4: Cash income | E4: {=SUMIF('Transactions'!C2:C100,"Income",'Transactions'!I2:I100)} -> 137300
A5: Currency | B5: THB | D5: Business expenses | E5: {=_xlfn.SUMIFS('Transactions'!I2:I100,'Transactions'!C2:C100,"Expense",'Transactions'!F2:F100,"<>Personal")} -> 25540
A6: Business model | B6: Independent creative freelancer | D6: Personal expenses | E6: {=_xlfn.SUMIFS('Transactions'!I2:I100,'Transactions'!C2:C100,"Expense",'Transactions'!F2:F100,"Personal")} -> 37900
A7: Data status | B7: 100% fictional / sample | D7: Operating surplus | E7: {=E4-E5-E6} -> 73860
A8: Accounting basis | B8: Cash basis; transfers excluded from profit | D8: Savings & tax transfers | E8: {=SUMIF('Transactions'!C2:C100,"Transfer",'Transactions'!I2:I100)} -> 14000
D9: Net cash movement | E9: {=E7-E8} -> 59860
D10: Outstanding invoices | E10: {='Invoices'!F7} -> 62000
A12: Expense Category | B12: Amount (THB) | C12: Income Source | D12: Received (THB)
A13: Housing | B13: {=_xlfn.SUMIFS('Transactions'!I2:I100,'Transactions'!D2:D100,A13,'Transactions'!C2:C100,"Expense")} -> 16320 | C13: Brand Identity — Nova | D13: {=_xlfn.SUMIFS('Transactions'!I2:I100,'Transactions'!F2:F100,C13,'Transactions'!C2:C100,"Income")} -> 28500
A14: Food | B14: {=_xlfn.SUMIFS('Transactions'!I2:I100,'Transactions'!D2:D100,A14,'Transactions'!C2:C100,"Expense")} -> 12530 | C14: Website — Aster | D14: {=_xlfn.SUMIFS('Transactions'!I2:I100,'Transactions'!F2:F100,C14,'Transactions'!C2:C100,"Income")} -> 56000
A15: Transport | B15: {=_xlfn.SUMIFS('Transactions'!I2:I100,'Transactions'!D2:D100,A15,'Transactions'!C2:C100,"Expense")} -> 2600 | C15: Video Campaign — Orbit | D15: {=_xlfn.SUMIFS('Transactions'!I2:I100,'Transactions'!F2:F100,C15,'Transactions'!C2:C100,"Income")} -> 32500
A16: Business | B16: {=_xlfn.SUMIFS('Transactions'!I2:I100,'Transactions'!D2:D100,A16,'Transactions'!C2:C100,"Expense")} -> 24920 | C16: Social Media — Bloom | D16: {=_xlfn.SUMIFS('Transactions'!I2:I100,'Transactions'!F2:F100,C16,'Transactions'!C2:C100,"Income")} -> 18000
A17: Subscriptions | B17: {=_xlfn.SUMIFS('Transactions'!I2:I100,'Transactions'!D2:D100,A17,'Transactions'!C2:C100,"Expense")} -> 3340 | C17: UX Audit — Meridian | D17: {=_xlfn.SUMIFS('Transactions'!I2:I100,'Transactions'!F2:F100,C17,'Transactions'!C2:C100,"Income")} -> 0
A18: Personal | B18: {=_xlfn.SUMIFS('Transactions'!I2:I100,'Transactions'!D2:D100,A18,'Transactions'!C2:C100,"Expense")} -> 950 | C18: Other | D18: {=_xlfn.SUMIFS('Transactions'!I2:I100,'Transactions'!F2:F100,C18,'Transactions'!C2:C100,"Income")} -> 2300
A19: Health | B19: {=_xlfn.SUMIFS('Transactions'!I2:I100,'Transactions'!D2:D100,A19,'Transactions'!C2:C100,"Expense")} -> 470
A20: Shopping | B20: {=_xlfn.SUMIFS('Transactions'!I2:I100,'Transactions'!D2:D100,A20,'Transactions'!C2:C100,"Expense")} -> 1890
A21: Entertainment | B21: {=_xlfn.SUMIFS('Transactions'!I2:I100,'Transactions'!D2:D100,A21,'Transactions'!C2:C100,"Expense")} -> 420

Sheet Transactions
A1: Transaction ID | B1: Date | C1: Type | D1: Category | E1: Description | F1: Project / Area | G1: Payment Method | H1: Account | I1: Amount (THB) | J1: Status | K1: Cash Flow (THB)
A2: TX-0007 | B2: 46266 | C2: Expense | D2: Housing | E2: Rent | F2: Personal | G2: Bank Transfer | H2: Operating | I2: 14500 | J2: Completed | K2: {=IF(C2="Income",I2,-I2)} -> -14500
A3: TX-0009 | B3: 46267 | C3: Expense | D3: Food | E3: Groceries | F3: Personal | G3: Bank Transfer | H3: Operating | I3: 2850 | J3: Completed | K3: {=IF(C3="Income",I3,-I3)} -> -2850
A4: TX-0008 | B4: 46268 | C4: Expense | D4: Housing | E4: Electricity & water | F4: Personal | G4: Bank Transfer | H4: Operating | I4: 1820 | J4: Completed | K4: {=IF(C4="Income",I4,-I4)} -> -1820
A5: TX-0011 | B5: 46268 | C5: Expense | D5: Transport | E5: Metro pass | F5: Personal | G5: Bank Transfer | H5: Operating | I5: 1450 | J5: Completed | K5: {=IF(C5="Income",I5,-I5)} -> -1450
A6: TX-0010 | B6: 46269 | C6: Expense | D6: Food | E6: Lunch & coffee | F6: Personal | G6: Card | H6: Operating | I6: 580 | J6: Completed | K6: {=IF(C6="Income",I6,-I6)} -> -580
A7: TX-0001 | B7: 46270 | C7: Income | D7: Client payment | E7: Brand Identity — Nova | F7: Brand Identity — Nova | G7: Bank Transfer | H7: Operating | I7: 28500 | J7: Completed | K7: {=IF(C7="Income",I7,-I7)} -> 28500
A8: TX-0012 | B8: 46270 | C8: Expense | D8: Business | E8: Stock footage | F8: Video Campaign — Orbit | G8: Bank Transfer | H8: Operating | I8: 1250 | J8: Completed | K8: {=IF(C8="Income",I8,-I8)} -> -1250
A9: TX-0013 | B9: 46272 | C9: Expense | D9: Business | E9: Fonts & assets | F9: Brand Identity — Nova | G9: Card | H9: Operating | I9: 890 | J9: Completed | K9: {=IF(C9="Income",I9,-I9)} -> -890
A10: TX-0014 | B10: 46273 | C10: Expense | D10: Business | E10: Cloud hosting | F10: Website — Aster | G10: Bank Transfer | H10: Operating | I10: 1250 | J10: Completed | K10: {=IF(C10="Income",I10,-I10)} -> -1250
A11: TX-0015 | B11: 46273 | C11: Expense | D11: Subscriptions | E11: Adobe Creative Cloud | F11: Personal | G11: Bank Transfer | H11: Operating | I11: 2190 | J11: Completed | K11: {=IF(C11="Income",I11,-I11)} -> -2190
A12: TX-0002 | B12: 46274 | C12: Income | D12: Client payment | E12: Website — Aster | F12: Website — Aster | G12: Bank Transfer | H12: Operating | I12: 42000 | J12: Completed | K12: {=IF(C12="Income",I12,-I12)} -> 42000
A13: TX-0016 | B13: 46275 | C13: Expense | D13: Business | E13: Freelance designer | F13: Website — Aster | G13: Bank Transfer | H13: Operating | I13: 9200 | J13: Completed | K13: {=IF(C13="Income",I13,-I13)} -> -9200
... A36: TX-0035 | B36: 46295 | C36: Transfer | D36: Tax | E36: Estimated income tax transfer | F36: Personal | G36: Bank Transfer | H36: Savings / Tax | I36: 6500 | J36: Completed | K36: {=IF(C36="Income",I36,-I36)} -> -6500

Sheet Projects
A1: Project | B1: Client | C1: Contract Value | D1: Cash Received | E1: Direct Costs | F1: Cash Profit
A2: Brand Identity — Nova | B2: Nova Studio | C2: 35000 | D2: {=_xlfn.SUMIFS('Transactions'!$I$2:$I$100,'Transactions'!$F$2:$F$100,A2,'Transactions'!$C$2:$C$100,"Income")} -> 28500 | E2: {=_xlfn.SUMIFS('Transactions'!$I$2:$I$100,'Transactions'!$F$2:$F$100,A2,'Transactions'!$C$2:$C$100,"Expense")} -> 1680 | F2: {=D2-E2} -> 26820
A3: Website — Aster | B3: Aster Labs | C3: 68000 | D3: {=_xlfn.SUMIFS('Transactions'!$I$2:$I$100,'Transactions'!$F$2:$F$100,A3,'Transactions'!$C$2:$C$100,"Income")} -> 56000 | E3: {=_xlfn.SUMIFS('Transactions'!$I$2:$I$100,'Transactions'!$F$2:$F$100,A3,'Transactions'!$C$2:$C$100,"Expense")} -> 11340 | F3: {=D3-E3} -> 44660
A4: Video Campaign — Orbit | B4: Orbit Media | C4: 48000 | D4: {=_xlfn.SUMIFS('Transactions'!$I$2:$I$100,'Transactions'!$F$2:$F$100,A4,'Transactions'!$C$2:$C$100,"Income")} -> 32500 | E4: {=_xlfn.SUMIFS('Transactions'!$I$2:$I$100,'Transactions'!$F$2:$F$100,A4,'Transactions'!$C$2:$C$100,"Expense")} -> 7750 | F4: {=D4-E4} -> 24750
A5: Social Media — Bloom | B5: Bloom Co. | C5: 24000 | D5: {=_xlfn.SUMIFS('Transactions'!$I$2:$I$100,'Transactions'!$F$2:$F$100,A5,'Transactions'!$C$2:$C$100,"Income")} -> 18000 | E5: {=_xlfn.SUMIFS('Transactions'!$I$2:$I$100,'Transactions'!$F$2:$F$100,A5,'Transactions'!$C$2:$C$100,"Expense")} -> 1970 | F5: {=D5-E5} -> 16030
A6: UX Audit — Meridian | B6: Meridian Co. | C6: 22000 | D6: {=_xlfn.SUMIFS('Transactions'!$I$2:$I$100,'Transactions'!$F$2:$F$100,A6,'Transactions'!$C$2:$C$100,"Income")} -> 0 | E6: {=_xlfn.SUMIFS('Transactions'!$I$2:$I$100,'Transactions'!$F$2:$F$100,A6,'Transactions'!$C$2:$C$100,"Expense")} -> 2800 | F6: {=D6-E6} -> -2800
A7: TOTAL | C7: {=SUM(C2:C6)} -> 197000 | D7: {=SUM(D2:D6)} -> 135000 | E7: {=SUM(E2:E6)} -> 25540 | F7: {=SUM(F2:F6)} -> 109460

Sheet Invoices
A1: Invoice | B1: Project | C1: Client | D1: Issued | E1: Due Date | F1: Amount | G1: Status | H1: Notes
A2: INV-2609-001 | B2: Brand Identity — Nova | C2: Nova Studio | D2: 46268 | E2: 46299 | F2: 6500 | G2: Unpaid | H2: Final milestone
A3: INV-2609-002 | B3: Website — Aster | C3: Aster Labs | D3: 46291 | E3: 46321 | F3: 12000 | G3: Unpaid | H3: Remaining phase 2
A4: INV-2609-003 | B4: Video Campaign — Orbit | C4: Orbit Media | D4: 46290 | E4: 46310 | F4: 15500 | G4: Unpaid | H4: Final cut
A5: INV-2609-004 | B5: Social Media — Bloom | C5: Bloom Co. | D5: 46294 | E5: 46324 | F5: 6000 | G5: Unpaid | H5: September balance
A6: INV-2609-005 | B6: UX Audit — Meridian | C6: Meridian Co. | D6: 46293 | E6: 46323 | F6: 22000 | G6: Unpaid | H6: Awaiting kickoff payment
E7: TOTAL UNPAID | F7: {=SUMIF(G2:G6,"Unpaid",F2:F6)} -> 62000

Sheet Read Me
A1: SAMPLE PERSONAL FINANCE WORKBOOK
A2: Owner | B2: Alex Morgan (fictional)
A3: Period | B3: September 2026
A4: Currency | B4: Thai baht (THB)
A5: Transactions | B5: Positive amounts; Type controls cash-flow sign. Savings and tax transfers are not expenses.
A6: Dashboard | B6: Income less business + personal expenses is operating surplus; net cash movement also deducts transfers.
A7: Projects | B7: Cash received and direct expense by project; other overhead excluded from project cash profit.
A8: Invoices | B8: Unpaid balances are not included in cash income. All sample records are fabricated.
